CCF.cpython-310-darwin.so
Marsh.cpython-310-darwin.so
transitspectroscopy/__init__.py
transitspectroscopy/_version.py
transitspectroscopy/jwst.py
transitspectroscopy/spectroscopy.py
transitspectroscopy/transitfitting.py
transitspectroscopy/utils.py
transitspectroscopy-0.3.12.dist-info/LICENCE
transitspectroscopy-0.3.12.dist-info/METADATA
transitspectroscopy-0.3.12.dist-info/WHEEL
transitspectroscopy-0.3.12.dist-info/top_level.txt
transitspectroscopy-0.3.12.dist-info/RECORD
