Metadata-Version: 2.1
Name: transitspectroscopy
Version: 0.3.12
Summary: transitspectroscopy: a library for all your transit spectroscopy needs
Home-page: http://github.com/nespinoza/transitspectroscopy
Author: Nestor Espinoza
Author-email: nespinoza@stsci.edu
License: MIT
Platform: UNKNOWN
Requires-Python: >=3.0
License-File: LICENCE
Requires-Dist: numpy
Requires-Dist: scipy
Requires-Dist: jwst
Requires-Dist: astropy
Requires-Dist: jdcal
